allforgraphs/__init__.py
allforgraphs/algorithms/__init__.py
allforgraphs/algorithms/dr.py
allforgraphs/algorithms/euler_gr.py
allforgraphs/algorithms/kr_max.py
allforgraphs/algorithms/kr_min.py
allforgraphs/algorithms/prima_max.py
allforgraphs/algorithms/prima_min.py
allforgraphs/matrices/__init__.py
allforgraphs/matrices/matr_inz.py
allforgraphs/matrices/matr_sm.py
allforgraphs/matrices/matr_vs.py
allforgraphs/matrices/tz.py
allforgraphs/matrices/wf.py
allforgraphs-1.0.1.dist-info/LICENSE
allforgraphs-1.0.1.dist-info/METADATA
allforgraphs-1.0.1.dist-info/WHEEL
allforgraphs-1.0.1.dist-info/top_level.txt
allforgraphs-1.0.1.dist-info/RECORD
