Metadata-Version: 2.1
Name: allforgraphs
Version: 1.0.1
Summary: Library for graphs.
Home-page: https://github.com/Katerok27153/allforgraphs.git
Author: katya,maria,olga
Author-email: 1132236136@pfur.ru
Project-URL: GitHub, https://github.com/Katerok27153/allforgraphs.git
Keywords: files speedfiles
Classifier: Programming Language :: Python :: 3.11
Classifier: License :: OSI Approved :: MIT License
Classifier: Operating System :: OS Independent
Requires-Python: >=3.6
License-File: LICENSE
Requires-Dist: requests>=2.25.1
Requires-Dist: numpy>=2.2.0
Requires-Dist: networkx>=3.4.2
